{"101487":137929,"Last Jedi":"Last Jedi","2017-12-15":"2018-04-10","3":1,"A lot of twists and deaths. I feel like the time on the island was a waste of time. Very little was accomplished. Rey never really was trained but some how is very good with a light saber and using the force. Snoke was not explained at all\\, which was frustrating. The Finn and Rose subplot was boring. Only one light saber battle and that is the best part of Star Wars. I didn't think Carrie Fisher's performance was all that great. Good movie but I was expecting much more.":"Incre\u00edble. Una pel\u00edcula que atenta directametne contra TODO lo establecido en Star Wars\\, plagada de errores argumentales\\, secuencias sin prop\u00f3sito o completamente rid\u00edculas (Leia voladora)\\, personajes mal desarrollados y otros (Luke y Yoda) totalmente cambiados con respecto a todo lo establecido\\, recordarle al director que esta es parte de una SAGA\\, como pel\u00edcula independiente podr\u00eda funcionar\\, pero cuando escribes para una serie debes recordar y tomar en cuenta lo antes establecido\\, especialmente porque habr\u00e1 personas que lo har\u00e1n a otros tal vez no les importe\\, depender\u00e1 de su grado de compromiso\\, pero te debes a los primeros porque ellos constituyen tu sector PRIORITARIO de p\u00fablico. A nivel t\u00e9cnico est\u00e1 bastante bien y se disfruta\\, pero Star Wars nunca ha sido solo eso. El guion es p\u00e9simo\\, la pel\u00edcula se siente largu\u00edsima y no sientes que lleve a ninguna parte\\, lo peor de todo es la extra\u00f1a muerte de Luke\\, queda mal planteada\\, se siente como una especie de enga\u00f1o al espectador. Con una sola pel\u00edcula Disney se ha cargado los elementos m\u00e1s importantes que hac\u00edan a Star Wars lo que era\\, muy mal\\, realmente es tr\u00e1gico.","true":false}