{"101487":153754,"Last Jedi":"Last Jedi","2017-12-15":"2018-01-04","3":5,"A lot of twists and deaths. I feel like the time on the island was a waste of time. Very little was accomplished. Rey never really was trained but some how is very good with a light saber and using the force. Snoke was not explained at all\\, which was frustrating. The Finn and Rose subplot was boring. Only one light saber battle and that is the best part of Star Wars. I didn't think Carrie Fisher's performance was all that great. Good movie but I was expecting much more.":"Meraviglioso\\, uno dei migliori Star Wars di sempre a mio parere\\, forse il miglior episodio dopo L'Impero Colpisce Ancora. Questo film aggiunge tanto all'epica di questo universo\\, ai suoi personaggi e al mito. Regia e effetti speciali da togliersi il cappello\\, scene di combattimento micidiali\\, personaggi vecchi e nuovi eccezionali. Non \u00e8 perfetto\\, qualche parte della sceneggiatura non \u00e8 esattamente approfondita bene (come la story-line di Finn)\\, ma per quanto mi riguarda sono sottigliezze. Riguardo le miriadi di critiche negative da parte dei fan\\, credo che gran parte del fandom di Star Wars non si meriti un film cos\u00ec bello.","true":false}