{"40636":"19945","TLOU2":"TLOU2","2020-08-05":"2020-06-20","10":10.0,"The Last of Us 2 represents how games should be made. The gameplay is beautiful\\, there's so much attention to the detail\\, the graphic (for PS4) is impressive\\, i can't even imagine on a version for PC. The story is compelling\\, unfortunately it has been criticized for his LGBT content inside\\, and yes\\, it seems to be politically deployed\\, but who cares? We are talking about the game\\, not thisThe Last of Us 2 represents how games should be made. The gameplay is beautiful\\, there's so much attention to the detail\\, the graphic (for PS4) is impressive\\, i can't even imagine on a version for PC. The story is compelling\\, unfortunately it has been criticized for his LGBT content inside\\, and yes\\, it seems to be politically deployed\\, but who cares? We are talking about the game\\, not this kind of stuff. Trust me\\, this game is a MUST PLAY\\, and the bad score that has from the User became from the \\\"spoilers\\\" that went on the game.\u2026 Expand":"Das Spiel ist Atemberaubend!Und das is milde ausgedruckt?!Eine Achterbahn der Gef\u00fchle.\\nDie Story ist super erz\u00e4hlt. Ob es jetz genau das is was viele erwartet haben? Glaube ich eher weniger\\, dennoch logisch und passend weitererz\u00e4hlt..\\nWeswegen man die ganzen 0 ranks getrost ignorieren kann! weil die wurden schon am Releasetag geschrieben und keiner kann das in 12 std durchspielen keiner!Das Spiel ist Atemberaubend!Und das is milde ausgedruckt?!Eine Achterbahn der Gef\u00fchle.Die Story ist super erz\u00e4hlt. Ob es jetz genau das is was viele erwartet haben? Glaube ich eher weniger\\, dennoch logisch und passend weitererz\u00e4hlt..Weswegen man die ganzen 0 ranks getrost ignorieren kann! weil die wurden schon am Releasetag geschrieben und keiner kann das in 12 std durchspielen keiner! Abgesehen davon ist die h\u00e4lfte der Kritik sinnlos und sagt einem nix wirklich aus und das nur weil die leute an einem punkt am spiel angekommen sind und denen das nicht passt was der Entwickler uns erz\u00e4hlt \u2026 Expand","true":false}