{"40636":"33377","TLOU2":"TLOU2","2020-08-05":"2020-06-25","10":5.0,"The Last of Us 2 represents how games should be made. The gameplay is beautiful\\, there's so much attention to the detail\\, the graphic (for PS4) is impressive\\, i can't even imagine on a version for PC. The story is compelling\\, unfortunately it has been criticized for his LGBT content inside\\, and yes\\, it seems to be politically deployed\\, but who cares? We are talking about the game\\, not thisThe Last of Us 2 represents how games should be made. The gameplay is beautiful\\, there's so much attention to the detail\\, the graphic (for PS4) is impressive\\, i can't even imagine on a version for PC. The story is compelling\\, unfortunately it has been criticized for his LGBT content inside\\, and yes\\, it seems to be politically deployed\\, but who cares? We are talking about the game\\, not this kind of stuff. Trust me\\, this game is a MUST PLAY\\, and the bad score that has from the User became from the \\\"spoilers\\\" that went on the game.\u2026 Expand":"Graphics? Unmatched. Music? What I expect\\, great. Story and character development? Not good (but I do like MOST of the new characters except for the extent of some of their developments). Looking at this from a writer\u2019s perspective in terms of craft\\, this story feels like a hot mess. Almost nothing is earned. I got the game because I wanted to see how ND handles a story like this (I hadGraphics? Unmatched. Music? What I expect\\, great. Story and character development? Not good (but I do like MOST of the new characters except for the extent of some of their developments). Looking at this from a writer\u2019s perspective in terms of craft\\, this story feels like a hot mess. Almost nothing is earned. I got the game because I wanted to see how ND handles a story like this (I had seen the spoilers but decided to give it a chance anyway because I love harsh stories). The only thing this game does right is making the player empathize with Ellie because we are pissed with her\u2014 but even from Abby\u2019s perspective\\, it isn\u2019t justified enough. I love writing imperfect\\, flawed characters\\, but this story\\, it was too prescriptive in terms of theme and the emotions it was trying to covey and that is where it falls short. Yeah I love the cruel world of TLOU universe but there are tedious ways to approach those themes and then there are ways not to; this game was just negligent and crude.\u2026 Expand","true":true}